flowkit_jwt_generator/__init__.py
flowkit_jwt_generator/_version.py
flowkit_jwt_generator/cli.py
flowkit_jwt_generator/fixtures.py
flowkit_jwt_generator/jwt.py
flowkit_jwt_generator-1.34.0.dist-info/METADATA
flowkit_jwt_generator-1.34.0.dist-info/WHEEL
flowkit_jwt_generator-1.34.0.dist-info/entry_points.txt
flowkit_jwt_generator-1.34.0.dist-info/top_level.txt
flowkit_jwt_generator-1.34.0.dist-info/RECORD
